isic_challenge_scoring/__init__.py
isic_challenge_scoring/__main__.py
isic_challenge_scoring/classification.py
isic_challenge_scoring/confusion.py
isic_challenge_scoring/load_csv.py
isic_challenge_scoring/load_image.py
isic_challenge_scoring/metrics.py
isic_challenge_scoring/segmentation.py
isic_challenge_scoring/task2.py
isic_challenge_scoring/types.py
isic_challenge_scoring/unzip.py
isic_challenge_scoring-5.7.0.dist-info/METADATA
isic_challenge_scoring-5.7.0.dist-info/WHEEL
isic_challenge_scoring-5.7.0.dist-info/entry_points.txt
isic_challenge_scoring-5.7.0.dist-info/licenses/LICENSE
isic_challenge_scoring-5.7.0.dist-info/RECORD
