Metadata-Version: 2.4
Name: isic-challenge-scoring
Version: 5.7.0
Summary: Submission scoring for the ISIC Challenge.
Project-URL: Repository, https://github.com/ImageMarkup/isic-challenge-scoring
Project-URL: Bug Reports, https://github.com/ImageMarkup/isic-challenge-scoring/issues
Maintainer-email: ISIC Archive <support@isic-archive.com>
License: Apache 2.0
License-File: LICENSE
Keywords: challenge,isic,isic-challenge,scoring
Classifier: Development Status :: 5 - Production/Stable
Classifier: License :: OSI Approved :: Apache Software License
Classifier: Operating System :: OS Independent
Classifier: Programming Language :: Python
Classifier: Programming Language :: Python :: 3
Classifier: Programming Language :: Python :: 3.13
Requires-Python: >=3.13
Requires-Dist: click
Requires-Dist: click-pathlib
Requires-Dist: numpy
Requires-Dist: pandas>=1.1
Requires-Dist: pillow>=7
Requires-Dist: rdp
Requires-Dist: scikit-learn
Requires-Dist: scipy
Requires-Dist: zipfile-deflate64
